losalina/hypernetwork.py
losalina-1.0.0.dist-info/METADATA
losalina-1.0.0.dist-info/WHEEL
losalina-1.0.0.dist-info/top_level.txt
losalina-1.0.0.dist-info/RECORD
